[{"newModel": 0, "parent": "-1", "is_meaningful": "yes", "children": ["14"], "leaf_group": ["3", "4", "9", "11", "14", "18", "19", "20", "21", "22", "23", "27", "30", "36", "39", "51", "52", "54", "60", "63", "64", "68", "69", "72", "75", "81", "83", "86", "94", "96", "97", "99", "102", "103", "104", "105", "106", "107", "109", "111", "112", "113", "115", "117", "118", "120", "122", "123", "124", "125", "126", "127", "140", "141", "142", "143", "144"], "next_rep": "-1", "label": ["0", "bedroom"], "rule": ["bedroom", "->", "inside"], "unary_descriptor_ZAligned": ["-7.39078e-10", "1.96515", "1.96515", "2.81838", "2.34004", "0.830279", "0.697261", "1.19077", "0.635982", "0.792552", "0.675917", "0.485083", "0.852836", "0.612052", "1.39341", "0.644914", "0.355086", "0.216445", "0.474529", "0.15602", "0.153006"], "binary_descriptor_BBoxIn3D": ["1.58719", "3.57876", "-2.95631e-08", "95.1889", "116.314", "78.6059"], "proxy_box": ["1.58719", "3.57876", "-2.95631e-08", "95.1889", "116.314", "78.6059"], "confidence": "1", "collada_label": "NULL"}, {"newModel": 1, "parent": "10", "is_meaningful": "yes", "children": [], "leaf_group": ["3", "4", "9", "11", "64"], "next_rep": "-1", "label": ["119", "nightstand"], "rule": null, "unary_descriptor_ZAligned": ["-4.02985e-10", "0.58563", "0.58563", "0.452756", "0.340058", "0.751084", "1.29348", "0.58067", "0.332186", "0.136936", "0.109996", "0.202255", "0.803264", "1.477", "0.543849", "0.595122", "0.404878", "0.149746", "0.202488", "0.162143", "0.485623"], "binary_descriptor_BBoxIn3D": ["4.90848", "3.57876", "-1.61194e-08", "18.5108", "21.689", "23.4252"], "proxy_box": ["4.90848", "3.57876", "-1.61194e-08", "18.5108", "21.689", "23.4252"], "confidence": "1", "collada_label": "NULL"}, {"newModel": 2, "parent": "13", "is_meaningful": "yes", "children": [], "leaf_group": ["18", "19", "20", "21", "22", "23", "52", "140", "141", "142", "143"], "next_rep": "-1", "label": ["120", "closet"], "rule": null, "unary_descriptor_ZAligned": ["5.6932e-10", "1.96515", "1.96515", "1.10568", "0.577625", "0.522415", "1.77732", "0.293935", "0.835608", "0.354738", "0.204196", "0.585842", "0.575626", "1.65148", "0.348552", "0.6793", "0.3207", "0.192769", "0.316439", "0.188474", "0.302318"], "binary_descriptor_BBoxIn3D": ["3.2333", "93.209", "2.27728e-08", "47.4606", "116.314", "78.6059"], "proxy_box": ["3.2333", "93.209", "2.27728e-08", "47.4606", "116.314", "78.6059"], "confidence": "1", "collada_label": "NULL"}, {"newModel": 3, "parent": "6", "is_meaningful": "yes", "children": [], "leaf_group": ["27", "30", "36", "39", "51", "54", "60", "63", "68", "69", "72", "75", "81", "83", "86", "111", "112", "117", "118", "122", "123", "127", "144"], "next_rep": "-1", "label": ["37", "bed"], "rule": ["bed", "->", "mattress", ",", "bed", "frame"], "unary_descriptor_ZAligned": ["1.85954e-08", "1.11927", "1.11927", "2.04864", "1.01985", "0.49782", "0.546348", "0.911176", "0.431623", "0.761722", "0.365597", "0.207238", "0.479961", "0.272066", "1.76414", "0.64425", "0.35575", "0.101496", "0.383122", "0.401222", "0.11416"], "binary_descriptor_BBoxIn3D": ["1.58719", "30.2705", "7.43817e-07", "83.5327", "71.0646", "44.7708"], "proxy_box": ["1.58719", "30.2705", "7.43817e-07", "83.5327", "71.0646", "44.7708"], "confidence": "1", "collada_label": "NULL"}, {"newModel": 4, "parent": "11", "is_meaningful": "yes", "children": [], "leaf_group": ["14", "94", "96", "97", "99", "103", "104", "105", "106", "107", "109", "113", "115", "120", "124", "125", "126"], "next_rep": "-1", "label": ["44", "desk"], "rule": null, "unary_descriptor_ZAligned": ["-7.39078e-10", "0.745472", "0.745473", "0.984253", "0.49213", "0.500004", "0.7574", "0.660158", "0.481016", "0.29091", "0.162764", "0.251058", "0.559498", "0.863009", "0.648311", "0.562741", "0.437259", "0.100337", "0.176805", "0.148078", "0.57478"], "binary_descriptor_BBoxIn3D": ["55.8188", "92.5308", "-2.95631e-08", "95.1889", "112.216", "29.8189"], "proxy_box": ["55.8188", "92.5308", "-2.95631e-08", "95.1889", "112.216", "29.8189"], "confidence": "1", "collada_label": "NULL"}, {"newModel": 5, "parent": "8", "is_meaningful": "yes", "children": [], "leaf_group": ["102"], "next_rep": "-1", "label": ["8", "pillow"], "rule": null, "unary_descriptor_ZAligned": ["0.431755", "0.609845", "0.17809", "0.979613", "0.324208", "0.330955", "0.181796", "1.82047", "0.503955", "0.267971", "0.0966482", "0.0493687", "0.360666", "0.184231", "1.95768", "0.12818", "0.87182", "0.217159", "0.267385", "0.235388", "0.280068"], "binary_descriptor_BBoxIn3D": ["4.66019", "31.0503", "17.2702", "17.6285", "70.2348", "24.3938"], "proxy_box": ["4.66019", "31.0503", "17.2702", "17.6285", "70.2348", "24.3938"], "confidence": "1", "collada_label": "NULL"}, {"newModel": 6, "parent": "7", "is_meaningful": "yes", "children": ["3", "8"], "leaf_group": ["27", "30", "36", "39", "51", "54", "60", "63", "68", "69", "72", "75", "81", "83", "86", "102", "111", "112", "117", "118", "122", "123", "127", "144"], "next_rep": "-1", "label": ["34", "bed", "and", "supported"], "rule": ["bed", "and", "supported", "->", "table", "lamp", ",", "blanket", ",", "bed", ",", "pillows"], "unary_descriptor_ZAligned": ["1.85954e-08", "1.11927", "1.11927", "2.04864", "1.01985", "0.49782", "0.546348", "0.911176", "0.439587", "0.771896", "0.355673", "0.195232", "0.460779", "0.252926", "1.82179", "0.598891", "0.401109", "0.08266", "0.381464", "0.430427", "0.105449"], "binary_descriptor_BBoxIn3D": ["1.58719", "30.2705", "7.43817e-07", "83.5327", "71.0646", "44.7708"], "proxy_box": ["1.58719", "30.2705", "7.43817e-07", "83.5327", "71.0646", "44.7708"], "confidence": "1", "collada_label": "NULL"}, {"newModel": 7, "parent": "14", "is_meaningful": "yes", "children": ["6", "10"], "leaf_group": ["3", "4", "9", "11", "27", "30", "36", "39", "51", "54", "60", "63", "64", "68", "69", "72", "75", "81", "83", "86", "102", "111", "112", "117", "118", "122", "123", "127", "144"], "next_rep": "-1", "label": ["79", "sleep", "area"], "rule": ["sleep", "area", "->", "rug", ",", "painting", ",", "book", "array", ",", "bed", "and", "supported", ",", "wall", "lamps", ",", "ottoman", "group", ",", "nightstand", "group"], "unary_descriptor_ZAligned": ["-4.02985e-10", "1.11927", "1.11927", "2.04864", "1.68715", "0.823545", "0.546348", "1.50736", "0.416074", "0.732965", "0.473885", "0.201208", "0.646532", "0.274512", "2.35521", "0.58292", "0.41708", "0.111692", "0.383979", "0.424032", "0.0802974"], "binary_descriptor_BBoxIn3D": ["1.58719", "3.57876", "-1.61194e-08", "83.5327", "71.0646", "44.7708"], "proxy_box": ["1.58719", "3.57876", "-1.61194e-08", "83.5327", "71.0646", "44.7708"], "confidence": "1", "collada_label": "NULL"}, {"newModel": 8, "parent": "6", "is_meaningful": "yes", "children": ["5"], "leaf_group": ["102"], "next_rep": "-1", "label": ["71", "pillows"], "rule": ["pillows", "->", "pillow"], "unary_descriptor_ZAligned": ["0.431755", "0.609845", "0.17809", "0.979613", "0.324208", "0.330955", "0.181796", "1.82047", "0.503955", "0.267971", "0.0966482", "0.0493687", "0.360666", "0.184231", "1.95768", "0.12818", "0.87182", "0.217159", "0.267385", "0.235388", "0.280068"], "binary_descriptor_BBoxIn3D": ["4.66019", "31.0503", "17.2702", "17.6285", "70.2348", "24.3938"], "proxy_box": ["4.66019", "31.0503", "17.2702", "17.6285", "70.2348", "24.3938"], "confidence": "1", "collada_label": "NULL"}, {"newModel": 9, "parent": "14", "is_meaningful": "yes", "children": ["11"], "leaf_group": ["14", "94", "96", "97", "99", "103", "104", "105", "106", "107", "109", "113", "115", "120", "124", "125", "126"], "next_rep": "-1", "label": ["92", "desk", "area"], "rule": ["desk", "area", "->", "rug", ",", "trash", "bin", ",", "desk", "group", ",", "chair", "group"], "unary_descriptor_ZAligned": ["-7.39078e-10", "0.745472", "0.745473", "0.984253", "0.49213", "0.500004", "0.7574", "0.660158", "0.481016", "0.29091", "0.162764", "0.251058", "0.559498", "0.863009", "0.648311", "0.562741", "0.437259", "0.100337", "0.176805", "0.148078", "0.57478"], "binary_descriptor_BBoxIn3D": ["55.8188", "92.5308", "-2.95631e-08", "95.1889", "112.216", "29.8189"], "proxy_box": ["55.8188", "92.5308", "-2.95631e-08", "95.1889", "112.216", "29.8189"], "confidence": "1", "collada_label": "NULL"}, {"newModel": 10, "parent": "7", "is_meaningful": "yes", "children": ["1"], "leaf_group": ["3", "4", "9", "11", "64"], "next_rep": "-1", "label": ["118", "nightstand", "group"], "rule": ["nightstand", "group", "->", "telephone", ",", "table", "lamp", ",", "clock", ",", "plant", ",", "vase", ",", "bottle", ",", "bag", ",", "book", "array", ",", "pencil", "pot", ",", "box", ",", "book", ",", "photo", "frame", ",", "cell", "phone", ",", "nightstand"], "unary_descriptor_ZAligned": ["-4.02985e-10", "0.58563", "0.58563", "0.452756", "0.340058", "0.751084", "1.29348", "0.58067", "0.332186", "0.136936", "0.109996", "0.202255", "0.803264", "1.477", "0.543849", "0.595122", "0.404878", "0.149746", "0.202488", "0.162143", "0.485623"], "binary_descriptor_BBoxIn3D": ["4.90848", "3.57876", "-1.61194e-08", "18.5108", "21.689", "23.4252"], "proxy_box": ["4.90848", "3.57876", "-1.61194e-08", "18.5108", "21.689", "23.4252"], "confidence": "1", "collada_label": "NULL"}, {"newModel": 11, "parent": "9", "is_meaningful": "yes", "children": ["4"], "leaf_group": ["14", "94", "96", "97", "99", "103", "104", "105", "106", "107", "109", "113", "115", "120", "124", "125", "126"], "next_rep": "-1", "label": ["104", "desk", "group"], "rule": ["desk", "group", "->", "telephone", ",", "table", "lamp", ",", "clock", ",", "plant", ",", "book", "array", ",", "book", ",", "desk", ",", "laptop", ",", "desktop", ",", "printer"], "unary_descriptor_ZAligned": ["-7.39078e-10", "0.745472", "0.745473", "0.984253", "0.49213", "0.500004", "0.7574", "0.660158", "0.481016", "0.29091", "0.162764", "0.251058", "0.559498", "0.863009", "0.648311", "0.562741", "0.437259", "0.100337", "0.176805", "0.148078", "0.57478"], "binary_descriptor_BBoxIn3D": ["55.8188", "92.5308", "-2.95631e-08", "95.1889", "112.216", "29.8189"], "proxy_box": ["55.8188", "92.5308", "-2.95631e-08", "95.1889", "112.216", "29.8189"], "confidence": "1", "collada_label": "NULL"}, {"newModel": 12, "parent": "14", "is_meaningful": "yes", "children": ["13"], "leaf_group": ["18", "19", "20", "21", "22", "23", "52", "140", "141", "142", "143"], "next_rep": "-1", "label": ["117", "storage", "area"], "rule": ["storage", "area", "->", "door", "set", ",", "box", ",", "cabinet", "group", ",", "on-wall", "shelf", "group", ",", "shelves", "group", ",", "closet", "group"], "unary_descriptor_ZAligned": ["5.6932e-10", "1.96515", "1.96515", "1.10568", "0.577625", "0.522415", "1.77732", "0.293935", "0.835608", "0.354738", "0.204196", "0.585842", "0.575626", "1.65148", "0.348552", "0.6793", "0.3207", "0.192769", "0.316439", "0.188474", "0.302318"], "binary_descriptor_BBoxIn3D": ["3.2333", "93.209", "2.27728e-08", "47.4606", "116.314", "78.6059"], "proxy_box": ["3.2333", "93.209", "2.27728e-08", "47.4606", "116.314", "78.6059"], "confidence": "1", "collada_label": "NULL"}, {"newModel": 13, "parent": "12", "is_meaningful": "yes", "children": ["2"], "leaf_group": ["18", "19", "20", "21", "22", "23", "52", "140", "141", "142", "143"], "next_rep": "-1", "label": ["125", "closet", "group"], "rule": ["closet", "group", "->", "guitar", ",", "folded", "blankets", ",", "closet"], "unary_descriptor_ZAligned": ["5.6932e-10", "1.96515", "1.96515", "1.10568", "0.577625", "0.522415", "1.77732", "0.293935", "0.835608", "0.354738", "0.204196", "0.585842", "0.575626", "1.65148", "0.348552", "0.6793", "0.3207", "0.192769", "0.316439", "0.188474", "0.302318"], "binary_descriptor_BBoxIn3D": ["3.2333", "93.209", "2.27728e-08", "47.4606", "116.314", "78.6059"], "proxy_box": ["3.2333", "93.209", "2.27728e-08", "47.4606", "116.314", "78.6059"], "confidence": "1", "collada_label": "NULL"}, {"newModel": 14, "parent": "0", "is_meaningful": "yes", "children": ["7", "9", "12"], "leaf_group": ["3", "4", "9", "11", "14", "18", "19", "20", "21", "22", "23", "27", "30", "36", "39", "51", "52", "54", "60", "63", "64", "68", "69", "72", "75", "81", "83", "86", "94", "96", "97", "99", "102", "103", "104", "105", "106", "107", "109", "111", "112", "113", "115", "117", "118", "120", "122", "123", "124", "125", "126", "127", "140", "141", "142", "143", "144"], "next_rep": "-1", "label": ["76", "inside"], "rule": ["inside", "->", "door", "set", ",", "rug", ",", "plant", ",", "mirror", ",", "floor", "lamp", ",", "air", "conditioner", ",", "human", ",", "surfboard", ",", "fireplace", ",", "ceiling", "fan", ",", "separation", "screen", ",", "paintings", ",", "ceiling", "lamps", ",", "rest", "area", ",", "sleep", "area", ",", "desk", "area", ",", "storage", "area", ",", "vanity", "area", ",", "window", "group", ",", "tv", "group", ",", "heater", "group", ",", "console", "area"], "unary_descriptor_ZAligned": ["-7.39078e-10", "1.96515", "1.96515", "2.81838", "2.34004", "0.830279", "0.697261", "1.19077", "0.635982", "0.792552", "0.675917", "0.485083", "0.852836", "0.612052", "1.39341", "0.644914", "0.355086", "0.216445", "0.474529", "0.15602", "0.153006"], "binary_descriptor_BBoxIn3D": ["1.58719", "3.57876", "-2.95631e-08", "95.1889", "116.314", "78.6059"], "proxy_box": ["1.58719", "3.57876", "-2.95631e-08", "95.1889", "116.314", "78.6059"], "confidence": "1", "collada_label": "NULL"}]